ormgrop/__init__.py
ormgrop/collections.py
ormgrop-0.1.0.dist-info/LICENSE.md
ormgrop-0.1.0.dist-info/METADATA
ormgrop-0.1.0.dist-info/WHEEL
ormgrop-0.1.0.dist-info/top_level.txt
ormgrop-0.1.0.dist-info/RECORD
