Metadata-Version: 2.1
Name: ormgrop
Version: 0.1.0
Summary: DevL's own standard library for Python 3
Home-page: https://devl.github.io/ormgrop
Author: Lennart Fridén
License: MIT
Project-URL: Bug Reports, https://github.com/DevL/ormgrop/issues
Project-URL: Source, https://github.com/DevL/ormgrop
Keywords: utility library
Platform: UNKNOWN
Classifier: Development Status :: 2 - Pre-Alpha
Classifier: Intended Audience :: Developers
Classifier: Topic :: Software Development :: Libraries
Classifier: License :: OSI Approved :: MIT License
Classifier: Programming Language :: Python :: 3
Classifier: Programming Language :: Python :: 3.5
Classifier: Programming Language :: Python :: 3.6
Classifier: Programming Language :: Python :: 3.7
Classifier: Programming Language :: Python :: 3.8
Requires-Python: ~=3.5
Provides-Extra: test
Requires-Dist: pytest ; extra == 'test'
